AUTHORS
LICENCE
MANIFEST.in
README.md
setup.py
django_canihitit.egg-info/PKG-INFO
django_canihitit.egg-info/SOURCES.txt
django_canihitit.egg-info/dependency_links.txt
django_canihitit.egg-info/not-zip-safe
django_canihitit.egg-info/top_level.txt
djangocanihitit/__init__.py
djangocanihitit/admin.py
djangocanihitit/apps.py
djangocanihitit/lib.py
djangocanihitit/models.py
djangocanihitit/management/__init__.py
djangocanihitit/management/commands/__init__.py
djangocanihitit/management/commands/canicleanit.py
djangocanihitit/migrations/0001_initial.py
djangocanihitit/migrations/__init__.py